debug_toolbar_force/__init__.py
debug_toolbar_force/conf.py
debug_toolbar_force/defaults.py
debug_toolbar_force/middleware.py
debug_toolbar_force/settings.py
debug_toolbar_force/tests/__init__.py
debug_toolbar_force/tests/base.py
debug_toolbar_force/tests/helpers.py
debug_toolbar_force/tests/test_core.py
debug_toolbar_force/tests/factories/__init__.py
debug_toolbar_force/tests/factories/auth_user.py
debug_toolbar_force/tests/factories/factory_faker.py
debug_toolbar_force/tests/factories/sites_site.py
debug_toolbar_force/tests/foo/__init__.py
debug_toolbar_force/tests/foo/models.py
debug_toolbar_force/tests/foo/urls.py
debug_toolbar_force/tests/foo/views.py
debug_toolbar_force/tests/foo/management/__init__.py
debug_toolbar_force/tests/foo/management/commands/__init__.py
debug_toolbar_force/tests/foo/management/commands/debug_toolbar_force_create_test_data.py
django_debug_toolbar_force-0.2.dist-info/LICENSE_GPL2.0.txt
django_debug_toolbar_force-0.2.dist-info/LICENSE_LGPL_2.1.txt
django_debug_toolbar_force-0.2.dist-info/METADATA
django_debug_toolbar_force-0.2.dist-info/WHEEL
django_debug_toolbar_force-0.2.dist-info/top_level.txt
django_debug_toolbar_force-0.2.dist-info/RECORD
