Metadata-Version: 2.1
Name: django-debug-toolbar-force
Version: 0.2
Summary: Force debugging of partial- or non-HTML views in django-debug-toolbar.
Home-page: https://github.com/barseghyanartur/django-debug-toolbar-force/
Author: Artur Barseghyan
Author-email: artur.barseghyan@gmail.com
License: GPL-2.0-only OR LGPL-2.1-or-later
Project-URL: Bug Tracker, https://github.com/barseghyanartur/django-debug-toolbar-force/
Project-URL: Documentation, https://django-debug-toolbar-force.readthedocs.io/
Project-URL: Source Code, https://github.com/barseghyanartur/django-debug-toolbar-force/
Project-URL: Changelog, https://django-debug-toolbar-force.readthedocs.io/en/latest/changelog.html
Keywords: django,django-debug-toolbar
Classifier: Programming Language :: Python :: 3.7
Classifier: Programming Language :: Python :: 3.8
Classifier: Programming Language :: Python :: 3.9
Classifier: Programming Language :: Python :: 3.10
Classifier: Programming Language :: Python :: 3.11
Classifier: Framework :: Django
Classifier: Framework :: Django :: 2.2
Classifier: Framework :: Django :: 3.0
Classifier: Framework :: Django :: 3.1
Classifier: Framework :: Django :: 3.2
Classifier: Framework :: Django :: 4.0
Classifier: Framework :: Django :: 4.1
Classifier: Environment :: Web Environment
Classifier: License :: OSI Approved :: GNU General Public License v2 (GPLv2)
Classifier: License :: OSI Approved :: GNU Lesser General Public License v2 or later (LGPLv2+)
Classifier: Framework :: Django
Classifier: Intended Audience :: Developers
Classifier: Operating System :: OS Independent
Classifier: Development Status :: 4 - Beta
License-File: LICENSE_GPL2.0.txt
License-File: LICENSE_LGPL_2.1.txt
